{
  "id": "polar_arctic_prefab",
  "tags": [
    "polar",
    "rural"
  ],
  "width": 15,
  "height": 11,
  "weight": 2,
  "no_rotate": true,
  "rows": [
    ".MMM+MMMMM+MMM.",
    ".MaaFFFFFFFFFM.",
    ".MFFFFF(DDD)FM.",
    ".MFFFFFFFFFFFM.",
    ".MMM+MMMMM+MMM.",
    ".MaFFFFMFFFaaM.",
    ".MFFFFDMFFFFFM.",
    ".MMM+MMMFFFFFM.",
    ".MFFFFFMFF(D)M.",
    ".MFFFFF+FFFD)M.",
    ".MMM+MMMM+MMMM."
  ],
  "terrain": {
    ".": "TileSnow",
    "M": "TileMetalWall",
    "F": "TileFloor",
    "+": "TileDoor",
    "a": "TileCabinet",
    "(": "TileChairRight",
    ")": "TileChairLeft"
  },
  "furniture": {
    "D": "TileDesk"
  }
}